[
  {
    "url": "https://apcshop.eu/motoskola",
    "type": "category",
    "title": "MOTOŠKOLA | APC Shop",
    "meta_description": "",
    "breadcrumbs": [],
    "product_links": [],
    "pagination_links": []
  },
  {
    "url": "https://apcshop.eu/pozicovna",
    "type": "category",
    "title": "POŽIČOVŇA | APC Shop",
    "meta_description": "",
    "breadcrumbs": [],
    "product_links": [
      "https://apcshop.eu/kawasaki-ninja-650-1",
      "https://apcshop.eu/kawasaki-z900-rs"
    ],
    "pagination_links": []
  },
  {
    "url": "https://apcshop.eu/servis",
    "type": "category",
    "title": "SERVIS | APC Shop",
    "meta_description": "",
    "breadcrumbs": [],
    "product_links": [],
    "pagination_links": []
  },
  {
    "url": "https://apcshop.eu/stroje",
    "type": "category",
    "title": "STROJE | APC Shop",
    "meta_description": "",
    "breadcrumbs": [],
    "product_links": [
      "https://apcshop.eu/benelli-125-bn-be01a",
      "https://apcshop.eu/benelli-752s-be12b",
      "https://apcshop.eu/benelli-leoncino-250-be04s",
      "https://apcshop.eu/benelli-leoncino-500-trail",
      "https://apcshop.eu/gladiator-x1000g3-mud-version-4",
      "https://apcshop.eu/gladiator-x1000g3-mud-version-3",
      "https://apcshop.eu/gladiator-x1000g3-premium-t3b",
      "https://apcshop.eu/gladiator-x1000g3-mud-version-11",
      "https://apcshop.eu/gladiator-x1000g3-overland",
      "https://apcshop.eu/gladiator-x1000g3-mud-version",
      "https://apcshop.eu/gladiator-x1000g3-mud-version-12",
      "https://apcshop.eu/gladiator-x520-t3b",
      "https://apcshop.eu/gladiator-x1000g3-mud-version-8",
      "https://apcshop.eu/gladiator-x1000g3-mud-version-10",
      "https://apcshop.eu/gladiator-x1000g3-mud-version-7",
      "https://apcshop.eu/gladiator-x1000g3-mud-version-9",
      "https://apcshop.eu/gladiator-x1000g3-mud-version-6",
      "https://apcshop.eu/gladiator-x1000g3-mud-version-5",
      "https://apcshop.eu/goes-terrox-1000-l7e",
      "https://apcshop.eu/goes-terrox-1000-t3b",
      "https://apcshop.eu/goes-terrox-1000-limited-l7e",
      "https://apcshop.eu/goes-terrox-1000-limited-l7e-1",
      "https://apcshop.eu/indian-scout-classic",
      "https://apcshop.eu/kawasaki-brute-force-750-4x4-eps",
      "https://apcshop.eu/kawasaki-klx-230",
      "https://apcshop.eu/kawasaki-mule-pro-mx",
      "https://apcshop.eu/kawasaki-mule-sx-4x4",
      "https://apcshop.eu/kawasaki-ninja-1000-sx-kt002",
      "https://apcshop.eu/kawasaki-ninja-125-ks005",
      "https://apcshop.eu/kawasaki-ninja-650-ks004"
    ],
    "pagination_links": [
      "https://apcshop.eu/stroje?p=2",
      "https://apcshop.eu/stroje?p=3",
      "https://apcshop.eu/stroje?p=4",
      "https://apcshop.eu/stroje?p=5"
    ]
  },
  {
    "url": "https://apcshop.eu/stroje/stvorkolky",
    "type": "category",
    "title": "ŠTVORKOLKY - STROJE | APC Shop",
    "meta_description": "",
    "breadcrumbs": [],
    "product_links": [
      "https://apcshop.eu/gladiator-x1000g3-mud-version-4",
      "https://apcshop.eu/gladiator-x1000g3-mud-version-3",
      "https://apcshop.eu/gladiator-x1000g3-premium-t3b",
      "https://apcshop.eu/gladiator-x1000g3-mud-version-11",
      "https://apcshop.eu/gladiator-x1000g3-overland",
      "https://apcshop.eu/gladiator-x1000g3-mud-version",
      "https://apcshop.eu/gladiator-x1000g3-mud-version-12",
      "https://apcshop.eu/gladiator-x520-t3b",
      "https://apcshop.eu/gladiator-x1000g3-mud-version-8",
      "https://apcshop.eu/gladiator-x1000g3-mud-version-10",
      "https://apcshop.eu/gladiator-x1000g3-mud-version-7",
      "https://apcshop.eu/gladiator-x1000g3-mud-version-9",
      "https://apcshop.eu/gladiator-x1000g3-mud-version-6",
      "https://apcshop.eu/gladiator-x1000g3-mud-version-5",
      "https://apcshop.eu/goes-terrox-1000-l7e",
      "https://apcshop.eu/goes-terrox-1000-t3b",
      "https://apcshop.eu/goes-terrox-1000-limited-l7e",
      "https://apcshop.eu/goes-terrox-1000-limited-l7e-1",
      "https://apcshop.eu/kawasaki-brute-force-750-4x4-eps",
      "https://apcshop.eu/kawasaki-mule-pro-mx",
      "https://apcshop.eu/kawasaki-mule-sx-4x4",
      "https://apcshop.eu/kayo-70",
      "https://apcshop.eu/kayo-at110-1",
      "https://apcshop.eu/kayo-au-110-1",
      "https://apcshop.eu/polaris-outlawr-110-efi-1",
      "https://apcshop.eu/polaris-outlawr-70-efi-1",
      "https://apcshop.eu/polaris-phoenixr-200-1",
      "https://apcshop.eu/polaris-rangerr-150-epi",
      "https://apcshop.eu/polaris-rzr-170-epi-1",
      "https://apcshop.eu/polaris-scrambler-xp-1000"
    ],
    "pagination_links": [
      "https://apcshop.eu/stroje/stvorkolky?p=2"
    ]
  },
  {
    "url": "https://apcshop.eu/stroje/stvorkolky/polaris-0",
    "type": "category",
    "title": "POLARIS - ŠTVORKOLKY - STROJE | APC Shop",
    "meta_description": "",
    "breadcrumbs": [],
    "product_links": [
      "https://apcshop.eu/polaris-outlawr-110-efi-1",
      "https://apcshop.eu/polaris-outlawr-70-efi-1",
      "https://apcshop.eu/polaris-phoenixr-200-1",
      "https://apcshop.eu/polaris-rangerr-150-epi",
      "https://apcshop.eu/polaris-rzr-170-epi-1",
      "https://apcshop.eu/polaris-scrambler-xp-1000",
      "https://apcshop.eu/polaris-scrambler-xp-1000-s-1",
      "https://apcshop.eu/polaris-sportsman-570",
      "https://apcshop.eu/polaris-sportsman-570-eps-1",
      "https://apcshop.eu/polaris-sportsman-570-eps-agri-pro-1",
      "https://apcshop.eu/polaris-sportsman-570-eps-black-edition-1",
      "https://apcshop.eu/polaris-sportsman-570-eps-hunter-edition-1",
      "https://apcshop.eu/polaris-sportsman-570-eps-sp-1",
      "https://apcshop.eu/polaris-sportsman-570-eps-sp-ohlins-se-1",
      "https://apcshop.eu/polaris-sportsman-570-touring",
      "https://apcshop.eu/polaris-sportsman-6x6-570-eps-1",
      "https://apcshop.eu/polaris-sportsman-6x6-570-eps-stealth-black-1",
      "https://apcshop.eu/polaris-sportsman-touring-570-eps-1",
      "https://apcshop.eu/polaris-sportsman-touring-570-eps-sp-1",
      "https://apcshop.eu/polaris-sportsman-touring-xp-1000-1",
      "https://apcshop.eu/polaris-sportsman-x2-570-eps",
      "https://apcshop.eu/polaris-sportsman-x2-570-eps-nordic-pro-1",
      "https://apcshop.eu/polaris-sportsman-xp-1000",
      "https://apcshop.eu/polaris-sportsman-xp-1000-s-1",
      "https://apcshop.eu/polaris-sportsmanr-110-efi-1"
    ],
    "pagination_links": []
  }
]